[{"id": 1463724370384150532, "date": "Thu Nov 25 04:20:59 +0000 2021", "text": "b'#RealMadrid #Benzema #ChampionsLeague #football'", "user_id": 1438141958325559307, "user_name": "@ABHIMD7", "location": {}, "retweeted": false}, {"id": 1463758005527318529, "date": "Thu Nov 25 06:34:38 +0000 2021", "text": "b'@Benzema @realmadrid @ChampionsLeague Nice game'", "user_id": 1458729911510835203, "user_name": "@JackieMbwana", "location": {}, "retweeted": false}, {"id": 1463728885460344841, "date": "Thu Nov 25 04:38:55 +0000 2021", "text": "b'@Benzema @realmadrid @ChampionsLeague Best of luck'", "user_id": 1463432961601196035, "user_name": "@ImranAl03520112", "location": {}, "retweeted": false}, {"id": 1463718111434129410, "date": "Thu Nov 25 03:56:06 +0000 2021", "text": "b'RT @NichekiHewani: Benzema'", "user_id": 932946757302054913, "user_name": "@IreneModest", "location": {}, "retweeted": true, "RT_text": "b'Benzema'", "RT_user_id": 572221008, "RT_user_name": "@NichekiHewani"}, {"id": 1463744423418904578, "date": "Thu Nov 25 05:40:40 +0000 2021", "text": "b'RT @realmadridarab: @Benzema \\xf0\\x9f\\xa4\\x9c @Benzema \\xf0\\x9f\\xa4\\x9b  #UCL https://t.co/X9umGh2jLD'", "user_id": 2279243359, "user_name": "@_alram_", "location": {}, "retweeted": true, "RT_text": "b'@Benzema \\xf0\\x9f\\xa4\\x9c @Benzema \\xf0\\x9f\\xa4\\x9b  #UCL https://t.co/X9umGh2jLD'", "RT_user_id": 153436029, "RT_user_name": "@realmadridarab"}, {"id": 1463732847156641795, "date": "Thu Nov 25 04:54:40 +0000 2021", "text": "b'RT @realmadridarab: @Benzema \\xf0\\x9f\\xa4\\x9c @Benzema \\xf0\\x9f\\xa4\\x9b  #UCL https://t.co/X9umGh2jLD'", "user_id": 3284108299, "user_name": "@almshali323", "location": {}, "retweeted": true, "RT_text": "b'@Benzema \\xf0\\x9f\\xa4\\x9c @Benzema \\xf0\\x9f\\xa4\\x9b  #UCL https://t.co/X9umGh2jLD'", "RT_user_id": 153436029, "RT_user_name": "@realmadridarab"}, {"id": 1463719585119707138, "date": "Thu Nov 25 04:01:58 +0000 2021", "text": "b'RT @realmadrid: \\xf0\\x9f\\x99\\x8c @Benzema \\xf0\\x9f\\x99\\x8c #UCL https://t.co/Tn8UC12iI4'", "user_id": 1009770623172841473, "user_name": "@zizymatique", "location": {}, "retweeted": true, "RT_text": "b'\\xf0\\x9f\\x99\\x8c @Benzema \\xf0\\x9f\\x99\\x8c #UCL https://t.co/Tn8UC12iI4'", "RT_user_id": 14872237, "RT_user_name": "@realmadrid"}, {"id": 1463719544044851207, "date": "Thu Nov 25 04:01:48 +0000 2021", "text": "b'RT @realmadrid: \\xf0\\x9f\\x99\\x8c @Benzema \\xf0\\x9f\\x99\\x8c #UCL https://t.co/Tn8UC12iI4'", "user_id": 3078669797, "user_name": "@mgl1807", "location": {}, "retweeted": true, "RT_text": "b'\\xf0\\x9f\\x99\\x8c @Benzema \\xf0\\x9f\\x99\\x8c #UCL https://t.co/Tn8UC12iI4'", "RT_user_id": 14872237, "RT_user_name": "@realmadrid"}, {"id": 1463719335155879945, "date": "Thu Nov 25 04:00:58 +0000 2021", "text": "b'RT @realmadrid: \\xf0\\x9f\\x99\\x8c @Benzema \\xf0\\x9f\\x99\\x8c #UCL https://t.co/Tn8UC12iI4'", "user_id": 922304929863258112, "user_name": "@oswaldo_Man15", "location": {}, "retweeted": true, "RT_text": "b'\\xf0\\x9f\\x99\\x8c @Benzema \\xf0\\x9f\\x99\\x8c #UCL https://t.co/Tn8UC12iI4'", "RT_user_id": 14872237, "RT_user_name": "@realmadrid"}, {"id": 1463718771009404935, "date": "Thu Nov 25 03:58:44 +0000 2021", "text": "b'RT @realmadrid: \\xf0\\x9f\\x99\\x8c @Benzema \\xf0\\x9f\\x99\\x8c #UCL https://t.co/Tn8UC12iI4'", "user_id": 1017424589226496000, "user_name": "@ernestmarcelo1", "location": {}, "retweeted": true, "RT_text": "b'\\xf0\\x9f\\x99\\x8c @Benzema \\xf0\\x9f\\x99\\x8c #UCL https://t.co/Tn8UC12iI4'", "RT_user_id": 14872237, "RT_user_name": "@realmadrid"}]